pr_prompt/__init__.py
pr_prompt/cli.py
pr_prompt/generator.py
pr_prompt/instructions/__init__.py
pr_prompt/instructions/description_instructions.py
pr_prompt/instructions/review_instructions.py
pr_prompt/markdown_builder.py
pr_prompt/py.typed
pr_prompt/utils/__init__.py
pr_prompt/utils/config.py
pr_prompt/utils/diff_parser.py
pr_prompt/utils/errors.py
pr_prompt/utils/file_filters.py
pr_prompt/utils/file_tree.py
pr_prompt/utils/git_client.py
pr_prompt/utils/markdown_parser.py
pr_prompt-1.2.1.dist-info/WHEEL
pr_prompt-1.2.1.dist-info/entry_points.txt
pr_prompt-1.2.1.dist-info/METADATA
pr_prompt-1.2.1.dist-info/RECORD
