Metadata-Version: 2.4
Name: pr-prompt
Version: 1.2.1
Summary: A tool to generate pull request prompts using git cli commands.
Author: Oskar Bonde
Author-email: Oskar Bonde <oskar.bonde@gmail.com>
License-Expression: MIT
Requires-Dist: gitpython>=3.1.45
Requires-Dist: typer>=0.19.1
Requires-Dist: tomli>=1.1.0 ; python_full_version < '3.11'
Requires-Python: >=3.9
